Workbook

Sheet Read Me
A1: Joby Aviation - Air Taxi Route Financial Model (Prototype)
A2: Financial Systems Analyst case study | Single illustrative route | 12-month monthly model with annual totals
A3: ILLUSTRATIVE PROTOTYPE - all inputs are hypothetical case-study assumptions, not Joby Aviation forecasts, guidance, or company-reported figures.
A5: Model status | B5: ='Financial Model'!$C$70 -> ALL 19 CHECKS PASS
A6: Active scenario | B6: =Assumptions!$C$5 -> Base
A7: FY route operating profit | B7: ='Financial Model'!$O$37 -> 198265.69
A9: Purpose
A10: Objective | B10: Show how air taxi operating drivers (flights, completion, seats, load factor, fare, unit costs) flow through to route-level financial performance, support near-term decisions (pricing, scheduling, cost targets), and provide a structure that can scale into Joby's commercial reporting infrastructure.
A11: Important | B11: ILLUSTRATIVE PROTOTYPE. Every input is a hypothetical assumption for a case study. Nothing in this workbook is a Joby Aviation forecast, guidance or company-reported figure.
A13: Workbook Map
A14: 1. Read Me | B14: Purpose, navigation, colour legend, methodology and extension roadmap.
A15: 2. Assumptions | B15: All editable inputs with units and source/notes. Scenario selector (cell C5). Column F 'Active Case' feeds the model.
A16: 3. Financial Model | B16: 12-month route model for the active scenario: driver build, operating metrics, route P&L, breakeven analysis and integrity checks. FY totals in column O.
A17: 4. Scenario Comparison | B17: Base / Upside / Downside computed side by side by an independent engine (rows 50+), with variance vs. Base.
A18: Planned: Sensitivity Analysis | B18: Not yet built. Flex inputs via the inp_* defined names (or the Assumptions column F cells) and read results from the out_* defined names.
A19: Planned: Executive Dashboard | B19: Not yet built. KPI tiles and charts should reference out_* names and the Scenario Comparison summary (rows 6-40) rather than raw cell addresses.
A21: Colour Legend
A22: Blue text, yellow fill | B22: Editable input (hypothetical, illustrative).
A23: Black text | B23: Formula - do not overwrite.
A24: Green text | B24: Link pulled from another tab.
A25: Navy / light-blue bands | B25: Headers and section titles.
A26: PASS / FAIL | B26: Integrity check results (green / red) at the bottom of Financial Model.
A28: How To Use
A29: Step 1 | B29: On Assumptions, choose the active scenario in C5 (Base, Upside, Downside).
A30: Step 2 | B30: Edit blue input cells only. Data validation blocks out-of-range rates and negative costs.
A31: Step 3 | B31: Review Financial Model (active case) and Scenario Comparison (all cases).
A32: Step 4 | B32: Confirm the model status above reads 'ALL ... CHECKS PASS'.
A34: Methodology
A35: Scheduled flights | B35: Operating days x scheduled flights per operating day.
A36: Completed flights | B36: Scheduled flights x flight completion rate (expected value).
A37: Available seats | B37: Completed flights x aircraft passenger seats per flight.
A38: Passengers flown | B38: Available seats x passenger load factor (load factor = Month 1 input x demand growth index, capped at 100%).
A39: Passenger revenue | B39: Passengers flown x average fare (Month 1 fare x fare growth index).
A40: Direct flight costs | B40: Completed flights x variable operating cost per completed flight (x cost growth index). Cancelled flights incur no variable cost.
A41: Passenger-variable costs | B41: Passengers flown x variable cost per passenger (x cost growth index).
A42: Contribution profit | B42: Passenger revenue - direct flight costs - passenger-variable costs. Flight-level economics before any fixed cost.
A43: Route operating profit | B43: Contribution profit - route-specific fixed costs. This is a route-level management measure, NOT EBITDA: corporate overhead, R&D, certification and aircraft ownership costs are excluded.
A44: Breakeven load factor | B44: (Direct flight costs [+ fixed route costs]) / (available seats x (fare - variable cost per passenger)). Flight-level version excludes fixed costs; route version includes them. Annual figure uses annual totals, i.e. a uniform load factor across the year.
A45: Annual rates | B45: Rates are weighted by their natural base (e.g. load factor = passengers / seats; fare = revenue / passengers), never simple averages of months. Any ratio with a zero denominator (e.g. margin with no revenue, cost per flight with no flights) shows 'n.m.' (not meaningful) rather than 0.
A46: Capacity cap | B46: Load factor is capped at 100%. The Financial Model shows how many months demand growth exceeds seat capacity (information only).
A47: Recalculation | B47: Workbook is set to fully recalculate on open. No circular references, no hard-coded results, no external links.
A49: Scaling Roadmap
A50: Multiple routes | B50: Add a Route ID to the Assumptions table (one column block or one row set per route), replicate the Financial Model block per route, and consolidate with SUMIFS on Route ID.
A51: Aircraft types / markets | B51: Move capacity and unit costs to an aircraft-type lookup and fares / demand to a market lookup; route rows reference them via INDEX/MATCH.
A52: Systems integration | B52: Replace hypothetical inputs with feeds from scheduling, booking, maintenance and ERP systems; keep this calculation layer and the integrity checks as the reconciliation control.

Sheet Assumptions
A1: Assumptions - Illustrative Air Taxi Route
A2: Edit blue cells only. Column F (Active Case) feeds every model calculation.
A3: ILLUSTRATIVE PROTOTYPE - all inputs are hypothetical case-study assumptions, not Joby Aviation forecasts, guidance, or company-reported figures.
G4: Legend
A5: Active scenario (select) | C5: Base | D5: <- choose Base, Upside or Downside; drives the Financial Model tab | G5: Blue text / yellow fill = editable input (hypothetical, illustrative)
A6: Active scenario index | C6: =MATCH($C$5,$C$9:$E$9,0) -> 1 | G6: Black text = formula (do not overwrite)
A7: Model integrity status | C7: ='Financial Model'!$C$70 -> ALL 19 CHECKS PASS | G7: Green text = link pulled from another tab
A9: Parameter | B9: Unit | C9: Base | D9: Upside | E9: Downside | F9: Active Case | G9: Source / Notes
A10: 1. Route & Service Setup (applies to all scenarios)
A11: Route name | B11: text | C11: Route A: Downtown - Airport | F11: =$C11 -> Route A: Downtown - Airport | G11: Illustrative placeholder (e.g., downtown vertiport to regional airport, ~15-25 miles). Not an announced Joby route.
A12: Service / aircraft type | B12: text | C12: Piloted eVTOL air taxi | F12: =$C12 -> Piloted eVTOL air taxi | G12: Illustrative 4-passenger piloted eVTOL configuration. Add a row per aircraft type when extending to a multi-aircraft fleet.
A13: Model start month | B13: date | C13: 46388 | D13: all cases | E13: all cases | F13: =$C13 -> 46388 | G13: Illustrative timing used to label periods only. Not a Joby launch date.
A14: Aircraft passenger seats per flight | B14: seats / flight | C14: 4 | D14: all cases | E14: all cases | F14: =$C14 -> 4 | G14: Illustrative; consistent with a pilot + 4 passenger eVTOL layout. Verify against current company disclosures before external use.
A15: Scheduled flights per operating day | B15: flights / day | C15: 32 | D15: all cases | E15: all cases | F15: =$C15 -> 32 | G15: Illustrative: e.g., 2 aircraft x 16 one-way flights over a ~14-hour operating window. One-way flights.
A16: Operating days per month | B16: days / month | C16: 28 | D16: all cases | E16: all cases | F16: =$C16 -> 28 | G16: Illustrative: allows ~2-3 non-operating days per month for weather, maintenance, holidays.
A18: 2. Scenario Operating & Unit Economics Drivers
A19: Flight completion rate | B19: % of scheduled | C19: 0.95 | D19: 0.97 | E19: 0.9 | F19: =INDEX($C19:$E19,$C$6) -> 0.95 | G19: Illustrative. Share of scheduled flights actually flown (weather, technical, ATC cancellations).
A20: Average fare per passenger (Month 1) | B20: $ / passenger | C20: 175 | D20: 190 | E20: 160 | F20: =INDEX($C20:$E20,$C$6) -> 175 | G20: Illustrative premium-rideshare-style price point for a ~15-25 mile urban trip. Net of discounts, excl. taxes.
A21: Passenger load factor (Month 1) | B21: % of seats | C21: 0.6 | D21: 0.68 | E21: 0.52 | F21: =INDEX($C21:$E21,$C$6) -> 0.6 | G21: Illustrative. Passengers flown / available seats on completed flights in Month 1.
A22: Variable operating cost per completed flight (Month 1) | B22: $ / completed flight | C22: 300 | D22: 280 | E22: 320 | F22: =INDEX($C22:$E22,$C$6) -> 300 | G22: Illustrative. Energy/charging, pilot cost per flight, maintenance reserves, landing & vertiport usage fees.
A23: Variable cost per passenger (Month 1) | B23: $ / passenger | C23: 12 | D23: 10 | E23: 15 | F23: =INDEX($C23:$E23,$C$6) -> 12 | G23: Illustrative. Payment processing, booking/distribution, passenger handling and per-passenger fees.
A24: Monthly route-specific fixed costs (Month 1) | B24: $ / month | C24: 90000 | D24: 85000 | E24: 100000 | F24: =INDEX($C24:$E24,$C$6) -> 90000 | G24: Illustrative. Route-dedicated vertiport lease, ground staff, local marketing. Excludes corporate overhead, R&D, certification, aircraft depreciation.
A26: 3. Optional Monthly Growth Rates (compounding from Month 1)
A27: Monthly fare growth rate | B27: % per month | C27: 0 | D27: 0.0025 | E27: -0.005 | F27: =INDEX($C27:$E27,$C$6) -> 0 | G27: Illustrative. Compounds monthly on the Month 1 fare. Negative = promotional pricing pressure.
A28: Monthly demand growth rate | B28: % per month | C28: 0.015 | D28: 0.02 | E28: 0.005 | F28: =INDEX($C28:$E28,$C$6) -> 0.015 | G28: Illustrative. Compounds monthly on the Month 1 load factor (modelled load factor capped at 100%).
A29: Monthly operating cost growth rate | B29: % per month | C29: 0 | D29: -0.0025 | E29: 0.005 | F29: =INDEX($C29:$E29,$C$6) -> 0 | G29: Illustrative. Compounds monthly on variable cost per flight, variable cost per passenger and fixed costs. Negative = efficiency gains.
A31: 4. Scenario Definitions
A32: Base | B32: Steady launch: 95% completion, $175 fare, 60% load factor building ~1.5%/month, flat unit costs.
A33: Upside | B33: Strong adoption: higher fare and load factor, faster demand ramp, better reliability and modest cost efficiencies.
A34: Downside | B34: Soft launch: discounted fares, weaker demand, more weather/technical cancellations and cost inflation.
A36: 5. Methodology Notes
A37: - Only column F (Active Case) is referenced by the Financial Model; it picks Base/Upside/Downside via INDEX on the scenario index.
A38: - Rates are stored as fractions (0.60 = 60%). Monthly growth compounds: value in month m = Month 1 value x (1 + rate)^(m - 1).
A39: - Volumes are expected values (scheduled flights x completion rate), so completed flights and passengers may be fractional.
A40: - Fixed costs here are route-specific only. Corporate overhead, R&D, certification and aircraft ownership costs are outside route operating profit.
A41: - To add a route: copy columns C:F into a new route block (or add a Route ID dimension) and point a new Financial Model block at it.

Sheet Financial Model
A1: Financial Model - Monthly Route Economics (12 months)
A2: Active scenario only. All values are formulas linked to the Assumptions tab.
A3: ILLUSTRATIVE PROTOTYPE - all inputs are hypothetical case-study assumptions, not Joby Aviation forecasts, guidance, or company-reported figures.
A4: ="Route: "&Assumptions!$F$11&" | Aircraft: "&Assumptions!$F$12&" | Active scenario: "&Assumptions!$C$5 -> Route: Route A: Downtown - Airport | Aircraft: Piloted eVTOL air taxi | Active scenario: Base
A6: Line item | B6: Unit | C6: Month 1 | D6: Month 2 | E6: Month 3 | F6: Month 4 | G6: Month 5 | H6: Month 6 | I6: Month 7 | J6: Month 8 | K6: Month 9 | L6: Month 10 | M6: Month 11 | N6: Month 12 | O6: FY Total | P6: Annual basis
A7: Month index | B7: # | C7: 1 | D7: =C7+1 -> 2 | E7: =D7+1 -> 3 | F7: =E7+1 -> 4 | G7: =F7+1 -> 5 | H7: =G7+1 -> 6 | I7: =H7+1 -> 7 | J7: =I7+1 -> 8 | K7: =J7+1 -> 9 | ... N7: =M7+1 -> 12
A8: Period | B8: month | C8: =EDATE(Assumptions!$F$13,C$7-1) -> 46388 | D8: =EDATE(Assumptions!$F$13,D$7-1) -> 46419 | E8: =EDATE(Assumptions!$F$13,E$7-1) -> 46447 | F8: =EDATE(Assumptions!$F$13,F$7-1) -> 46478 | G8: =EDATE(Assumptions!$F$13,G$7-1) -> 46508 | H8: =EDATE(Assumptions!$F$13,H$7-1) -> 46539 | I8: =EDATE(Assumptions!$F$13,I$7-1) -> 46569 | J8: =EDATE(Assumptions!$F$13,J$7-1) -> 46600 | ... N8: =EDATE(Assumptions!$F$13,N$7-1) -> 46722
A10: A. Driver Build (Active Case from Assumptions)
A11: Operating days | B11: days | C11: =Assumptions!$F$16 -> 28 | D11: =Assumptions!$F$16 -> 28 | E11: =Assumptions!$F$16 -> 28 | F11: =Assumptions!$F$16 -> 28 | G11: =Assumptions!$F$16 -> 28 | H11: =Assumptions!$F$16 -> 28 | I11: =Assumptions!$F$16 -> 28 | J11: =Assumptions!$F$16 -> 28 | ... N11: =Assumptions!$F$16 -> 28 | O11: =SUM(C11:N11) -> 336 | P11: Sum
A12: Scheduled flights per operating day | B12: flights / day | C12: =Assumptions!$F$15 -> 32 | D12: =Assumptions!$F$15 -> 32 | E12: =Assumptions!$F$15 -> 32 | F12: =Assumptions!$F$15 -> 32 | G12: =Assumptions!$F$15 -> 32 | H12: =Assumptions!$F$15 -> 32 | I12: =Assumptions!$F$15 -> 32 | J12: =Assumptions!$F$15 -> 32 | ... N12: =Assumptions!$F$15 -> 32 | O12: =IF(O11=0,"n.m.",O22/O11) -> 32 | P12: Weighted (flights / days)
A13: Fare growth index | B13: index | C13: =(1+Assumptions!$F$27)^(C$7-1) -> 1 | D13: =(1+Assumptions!$F$27)^(D$7-1) -> 1 | E13: =(1+Assumptions!$F$27)^(E$7-1) -> 1 | F13: =(1+Assumptions!$F$27)^(F$7-1) -> 1 | G13: =(1+Assumptions!$F$27)^(G$7-1) -> 1 | H13: =(1+Assumptions!$F$27)^(H$7-1) -> 1 | I13: =(1+Assumptions!$F$27)^(I$7-1) -> 1 | J13: =(1+Assumptions!$F$27)^(J$7-1) -> 1 | ... N13: =(1+Assumptions!$F$27)^(N$7-1) -> 1
A14: Demand growth index | B14: index | C14: =(1+Assumptions!$F$28)^(C$7-1) -> 1 | D14: =(1+Assumptions!$F$28)^(D$7-1) -> 1.015 | E14: =(1+Assumptions!$F$28)^(E$7-1) -> 1.030225 | F14: =(1+Assumptions!$F$28)^(F$7-1) -> 1.0456784 | G14: =(1+Assumptions!$F$28)^(G$7-1) -> 1.0613636 | H14: =(1+Assumptions!$F$28)^(H$7-1) -> 1.077284 | I14: =(1+Assumptions!$F$28)^(I$7-1) -> 1.0934433 | J14: =(1+Assumptions!$F$28)^(J$7-1) -> 1.1098449 | ... N14: =(1+Assumptions!$F$28)^(N$7-1) -> 1.1779489
A15: Operating cost growth index | B15: index | C15: =(1+Assumptions!$F$29)^(C$7-1) -> 1 | D15: =(1+Assumptions!$F$29)^(D$7-1) -> 1 | E15: =(1+Assumptions!$F$29)^(E$7-1) -> 1 | F15: =(1+Assumptions!$F$29)^(F$7-1) -> 1 | G15: =(1+Assumptions!$F$29)^(G$7-1) -> 1 | H15: =(1+Assumptions!$F$29)^(H$7-1) -> 1 | I15: =(1+Assumptions!$F$29)^(I$7-1) -> 1 | J15: =(1+Assumptions!$F$29)^(J$7-1) -> 1 | ... N15: =(1+Assumptions!$F$29)^(N$7-1) -> 1
A16: Flight completion rate | B16: % of scheduled | C16: =Assumptions!$F$19 -> 0.95 | D16: =Assumptions!$F$19 -> 0.95 | E16: =Assumptions!$F$19 -> 0.95 | F16: =Assumptions!$F$19 -> 0.95 | G16: =Assumptions!$F$19 -> 0.95 | H16: =Assumptions!$F$19 -> 0.95 | I16: =Assumptions!$F$19 -> 0.95 | J16: =Assumptions!$F$19 -> 0.95 | ... N16: =Assumptions!$F$19 -> 0.95 | O16: =IF(O22=0,"n.m.",O23/O22) -> 0.95 | P16: Weighted (completed / scheduled)
A17: Passenger load factor | B17: % of seats | C17: =MIN(1,MAX(0,Assumptions!$F$21*C14)) -> 0.6 | D17: =MIN(1,MAX(0,Assumptions!$F$21*D14)) -> 0.609 | E17: =MIN(1,MAX(0,Assumptions!$F$21*E14)) -> 0.618135 | F17: =MIN(1,MAX(0,Assumptions!$F$21*F14)) -> 0.62740703 | G17: =MIN(1,MAX(0,Assumptions!$F$21*G14)) -> 0.63681813 | H17: =MIN(1,MAX(0,Assumptions!$F$21*H14)) -> 0.6463704 | I17: =MIN(1,MAX(0,Assumptions!$F$21*I14)) -> 0.65606596 | J17: =MIN(1,MAX(0,Assumptions!$F$21*J14)) -> 0.66590695 | ... N17: =MIN(1,MAX(0,Assumptions!$F$21*N14)) -> 0.70676936 | O17: =IF(O24=0,"n.m.",O25/O24) -> 0.65206057 | P17: Weighted (passengers / seats)
A18: Variable operating cost per completed flight | B18: $ / flight | C18: =Assumptions!$F$22*C15 -> 300 | D18: =Assumptions!$F$22*D15 -> 300 | E18: =Assumptions!$F$22*E15 -> 300 | F18: =Assumptions!$F$22*F15 -> 300 | G18: =Assumptions!$F$22*G15 -> 300 | H18: =Assumptions!$F$22*H15 -> 300 | I18: =Assumptions!$F$22*I15 -> 300 | J18: =Assumptions!$F$22*J15 -> 300 | ... N18: =Assumptions!$F$22*N15 -> 300 | O18: =IF(O23=0,"n.m.",O30/O23) -> 300 | P18: Weighted (flight costs / flights)
A19: Variable cost per passenger | B19: $ / passenger | C19: =Assumptions!$F$23*C15 -> 12 | D19: =Assumptions!$F$23*D15 -> 12 | E19: =Assumptions!$F$23*E15 -> 12 | F19: =Assumptions!$F$23*F15 -> 12 | G19: =Assumptions!$F$23*G15 -> 12 | H19: =Assumptions!$F$23*H15 -> 12 | I19: =Assumptions!$F$23*I15 -> 12 | J19: =Assumptions!$F$23*J15 -> 12 | ... N19: =Assumptions!$F$23*N15 -> 12 | O19: =IF(O25=0,"n.m.",O31/O25) -> 12 | P19: Weighted (pax costs / passengers)
A21: B. Operating Metrics
A22: Scheduled flights | B22: flights | C22: =C11*C12 -> 896 | D22: =D11*D12 -> 896 | E22: =E11*E12 -> 896 | F22: =F11*F12 -> 896 | G22: =G11*G12 -> 896 | H22: =H11*H12 -> 896 | I22: =I11*I12 -> 896 | J22: =J11*J12 -> 896 | ... N22: =N11*N12 -> 896 | O22: =SUM(C22:N22) -> 10752 | P22: Sum
A23: Completed flights | B23: flights | C23: =C22*C16 -> 851.2 | D23: =D22*D16 -> 851.2 | E23: =E22*E16 -> 851.2 | F23: =F22*F16 -> 851.2 | G23: =G22*G16 -> 851.2 | H23: =H22*H16 -> 851.2 | I23: =I22*I16 -> 851.2 | J23: =J22*J16 -> 851.2 | ... N23: =N22*N16 -> 851.2 | O23: =SUM(C23:N23) -> 10214.4 | P23: Sum
A24: Available passenger seats | B24: seats | C24: =C23*Assumptions!$F$14 -> 3404.8 | D24: =D23*Assumptions!$F$14 -> 3404.8 | E24: =E23*Assumptions!$F$14 -> 3404.8 | F24: =F23*Assumptions!$F$14 -> 3404.8 | G24: =G23*Assumptions!$F$14 -> 3404.8 | H24: =H23*Assumptions!$F$14 -> 3404.8 | I24: =I23*Assumptions!$F$14 -> 3404.8 | J24: =J23*Assumptions!$F$14 -> 3404.8 | ... N24: =N23*Assumptions!$F$14 -> 3404.8 | O24: =SUM(C24:N24) -> 40857.6 | P24: Sum
A25: Passengers flown | B25: passengers | C25: =C24*C17 -> 2042.88 | D25: =D24*D17 -> 2073.5232 | E25: =E24*E17 -> 2104.626 | F25: =F24*F17 -> 2136.1954 | G25: =G24*G17 -> 2168.2384 | H25: =H24*H17 -> 2200.7619 | I25: =I24*I17 -> 2233.7734 | J25: =J24*J17 -> 2267.28 | ... N25: =N24*N17 -> 2406.4083 | O25: =SUM(C25:N25) -> 26641.63 | P25: Sum
A27: C. Route P&L
A28: Average fare | B28: $ / passenger | C28: =Assumptions!$F$20*C13 -> 175 | D28: =Assumptions!$F$20*D13 -> 175 | E28: =Assumptions!$F$20*E13 -> 175 | F28: =Assumptions!$F$20*F13 -> 175 | G28: =Assumptions!$F$20*G13 -> 175 | H28: =Assumptions!$F$20*H13 -> 175 | I28: =Assumptions!$F$20*I13 -> 175 | J28: =Assumptions!$F$20*J13 -> 175 | ... N28: =Assumptions!$F$20*N13 -> 175 | O28: =IF(O25=0,"n.m.",O29/O25) -> 175 | P28: Weighted avg (revenue / passengers)
A29: Passenger revenue | B29: $ | C29: =C25*C28 -> 357504 | D29: =D25*D28 -> 362866.56 | E29: =E25*E28 -> 368309.56 | F29: =F25*F28 -> 373834.2 | G29: =G25*G28 -> 379441.71 | H29: =H25*H28 -> 385133.34 | I29: =I25*I28 -> 390910.34 | J29: =J25*J28 -> 396774 | ... N29: =N25*N28 -> 421121.46 | O29: =SUM(C29:N29) -> 4662285.3 | P29: Sum
A30: Direct flight operating costs | B30: $ | C30: =C23*C18 -> 255360 | D30: =D23*D18 -> 255360 | E30: =E23*E18 -> 255360 | F30: =F23*F18 -> 255360 | G30: =G23*G18 -> 255360 | H30: =H23*H18 -> 255360 | I30: =I23*I18 -> 255360 | J30: =J23*J18 -> 255360 | ... N30: =N23*N18 -> 255360 | O30: =SUM(C30:N30) -> 3064320 | P30: Sum
A31: Passenger-variable costs | B31: $ | C31: =C25*C19 -> 24514.56 | D31: =D25*D19 -> 24882.278 | E31: =E25*E19 -> 25255.513 | F31: =F25*F19 -> 25634.345 | G31: =G25*G19 -> 26018.86 | H31: =H25*H19 -> 26409.143 | I31: =I25*I19 -> 26805.281 | J31: =J25*J19 -> 27207.36 | ... N31: =N25*N19 -> 28876.9 | O31: =SUM(C31:N31) -> 319699.56 | P31: Sum
A32: Total variable costs | B32: $ | C32: =C30+C31 -> 279874.56 | D32: =D30+D31 -> 280242.28 | E32: =E30+E31 -> 280615.51 | F32: =F30+F31 -> 280994.35 | G32: =G30+G31 -> 281378.86 | H32: =H30+H31 -> 281769.14 | I32: =I30+I31 -> 282165.28 | J32: =J30+J31 -> 282567.36 | ... N32: =N30+N31 -> 284236.9 | O32: =SUM(C32:N32) -> 3384019.6 | P32: Sum
A33: Contribution profit (flight-level) | B33: $ | C33: =C29-C32 -> 77629.44 | D33: =D29-D32 -> 82624.282 | E33: =E29-E32 -> 87694.046 | F33: =F29-F32 -> 92839.857 | G33: =G29-G32 -> 98062.854 | H33: =H29-H32 -> 103364.2 | I33: =I29-I32 -> 108745.06 | J33: =J29-J32 -> 114206.64 | ... N33: =N29-N32 -> 136884.56 | O33: =SUM(C33:N33) -> 1278265.7 | P33: Sum
A34: Contribution margin | B34: % of revenue | C34: =IF(C29=0,"n.m.",C33/C29) -> 0.21714286 | D34: =IF(D29=0,"n.m.",D33/D29) -> 0.2276988 | E34: =IF(E29=0,"n.m.",E33/E29) -> 0.23809875 | F34: =IF(F29=0,"n.m.",F33/F29) -> 0.248345 | G34: =IF(G29=0,"n.m.",G33/G29) -> 0.25843984 | H34: =IF(H29=0,"n.m.",H33/H29) -> 0.26838548 | I34: =IF(I29=0,"n.m.",I33/I29) -> 0.27818415 | J34: =IF(J29=0,"n.m.",J33/J29) -> 0.28783801 | ... O34: =IF(O29=0,"n.m.",O33/O29) -> 0.27417149 | P34: Weighted (annual contribution / revenue)
A35: Contribution profit per completed flight | B35: $ / flight | C35: =IF(C23=0,"n.m.",C33/C23) -> 91.2 | D35: =IF(D23=0,"n.m.",D33/D23) -> 97.068 | E35: =IF(E23=0,"n.m.",E33/E23) -> 103.02402 | F35: =IF(F23=0,"n.m.",F33/F23) -> 109.06938 | G35: =IF(G23=0,"n.m.",G33/G23) -> 115.20542 | H35: =IF(H23=0,"n.m.",H33/H23) -> 121.4335 | I35: =IF(I23=0,"n.m.",I33/I23) -> 127.755 | J35: =IF(J23=0,"n.m.",J33/J23) -> 134.17133 | ... O35: =IF(O23=0,"n.m.",O33/O23) -> 125.14349 | P35: Weighted (annual contribution / flights)
A36: Fixed route costs | B36: $ | C36: =Assumptions!$F$24*C15 -> 90000 | D36: =Assumptions!$F$24*D15 -> 90000 | E36: =Assumptions!$F$24*E15 -> 90000 | F36: =Assumptions!$F$24*F15 -> 90000 | G36: =Assumptions!$F$24*G15 -> 90000 | H36: =Assumptions!$F$24*H15 -> 90000 | I36: =Assumptions!$F$24*I15 -> 90000 | J36: =Assumptions!$F$24*J15 -> 90000 | ... N36: =Assumptions!$F$24*N15 -> 90000 | O36: =SUM(C36:N36) -> 1080000 | P36: Sum
A37: Route operating profit / (loss) | B37: $ | C37: =C33-C36 -> -12370.56 | D37: =D33-D36 -> -7375.7184 | E37: =E33-E36 -> -2305.9542 | F37: =F33-F36 -> 2839.8565 | G37: =G33-G36 -> 8062.8544 | H37: =H33-H36 -> 13364.197 | I37: =I33-I36 -> 18745.06 | J37: =J33-J36 -> 24206.636 | ... N37: =N33-N36 -> 46884.557 | O37: =SUM(C37:N37) -> 198265.69 | P37: Sum
A38: Route operating margin | B38: % of revenue | C38: =IF(C29=0,"n.m.",C37/C29) -> -0.034602578 | D38: =IF(D29=0,"n.m.",D37/D29) -> -0.020326255 | E38: =IF(E29=0,"n.m.",E37/E29) -> -0.0062609132 | F38: =IF(F29=0,"n.m.",F37/F29) -> 0.0075965669 | G38: =IF(G29=0,"n.m.",G37/G29) -> 0.021249257 | H38: =IF(H29=0,"n.m.",H37/H29) -> 0.034700182 | I38: =IF(I29=0,"n.m.",I37/I29) -> 0.047952326 | J38: =IF(J29=0,"n.m.",J37/J29) -> 0.061008625 | ... O38: =IF(O29=0,"n.m.",O37/O29) -> 0.042525431 | P38: Weighted (annual route op. profit / revenue)
A39: Cumulative route operating profit / (loss) | B39: $ | C39: =C37 -> -12370.56 | D39: =C39+D37 -> -19746.278 | E39: =D39+E37 -> -22052.233 | F39: =E39+F37 -> -19212.376 | G39: =F39+G37 -> -11149.522 | H39: =G39+H37 -> 2214.6755 | I39: =H39+I37 -> 20959.736 | J39: =I39+J37 -> 45166.372 | K39: =J39+K37 -> 74916.507 | ... N39: =M39+N37 -> 198265.69 | O39: =N39 -> 198265.69 | P39: End of period
A41: D. Breakeven Analysis
A42: Net margin per passenger (fare - variable cost per passenger) | B42: $ / passenger | C42: =C28-C19 -> 163 | D42: =D28-D19 -> 163 | E42: =E28-E19 -> 163 | F42: =F28-F19 -> 163 | G42: =G28-G19 -> 163 | H42: =H28-H19 -> 163 | I42: =I28-I19 -> 163 | J42: =J28-J19 -> 163 | ... N42: =N28-N19 -> 163 | O42: =IF(O25=0,"n.m.",(O29-O31)/O25) -> 163 | P42: Weighted ((revenue - pax costs) / passengers)
A43: Passenger margin if every seat were sold (100% load factor) | B43: $ | C43: =C24*C42 -> 554982.4 | D43: =D24*D42 -> 554982.4 | E43: =E24*E42 -> 554982.4 | F43: =F24*F42 -> 554982.4 | G43: =G24*G42 -> 554982.4 | H43: =H24*H42 -> 554982.4 | I43: =I24*I42 -> 554982.4 | J43: =J24*J42 -> 554982.4 | ... N43: =N24*N42 -> 554982.4 | O43: =SUM(C43:N43) -> 6659788.8 | P43: Sum
A44: Breakeven load factor - flight level (contribution = 0) | B44: % of seats | C44: =IF(C43>0,(C30)/C43,"n.m.") -> 0.4601227 | D44: =IF(D43>0,(D30)/D43,"n.m.") -> 0.4601227 | E44: =IF(E43>0,(E30)/E43,"n.m.") -> 0.4601227 | F44: =IF(F43>0,(F30)/F43,"n.m.") -> 0.4601227 | G44: =IF(G43>0,(G30)/G43,"n.m.") -> 0.4601227 | H44: =IF(H43>0,(H30)/H43,"n.m.") -> 0.4601227 | I44: =IF(I43>0,(I30)/I43,"n.m.") -> 0.4601227 | J44: =IF(J43>0,(J30)/J43,"n.m.") -> 0.4601227 | ... O44: =IF(O43>0,(O30)/O43,"n.m.") -> 0.4601227 | P44: Annual: total flight costs / total max margin
A45: Breakeven load factor - route (after fixed route costs) | B45: % of seats | C45: =IF(C43>0,(C30+C36)/C43,"n.m.") -> 0.62229 | D45: =IF(D43>0,(D30+D36)/D43,"n.m.") -> 0.62229 | E45: =IF(E43>0,(E30+E36)/E43,"n.m.") -> 0.62229 | F45: =IF(F43>0,(F30+F36)/F43,"n.m.") -> 0.62229 | G45: =IF(G43>0,(G30+G36)/G43,"n.m.") -> 0.62229 | H45: =IF(H43>0,(H30+H36)/H43,"n.m.") -> 0.62229 | I45: =IF(I43>0,(I30+I36)/I43,"n.m.") -> 0.62229 | J45: =IF(J43>0,(J30+J36)/J43,"n.m.") -> 0.62229 | ... O45: =IF(O43>0,(O30+O36)/O43,"n.m.") -> 0.62229 | P45: Annual: (flight + fixed costs) / total max margin
A46: Load factor headroom vs. route breakeven | B46: pct. points | C46: =IF(ISNUMBER(C45),C17-C45,"n.m.") -> -0.022290004 | D46: =IF(ISNUMBER(D45),D17-D45,"n.m.") -> -0.013290004 | E46: =IF(ISNUMBER(E45),E17-E45,"n.m.") -> -0.0041550042 | F46: =IF(ISNUMBER(F45),F17-F45,"n.m.") -> 0.0051170208 | G46: =IF(ISNUMBER(G45),G17-G45,"n.m.") -> 0.014528126 | H46: =IF(ISNUMBER(H45),H17-H45,"n.m.") -> 0.024080398 | I46: =IF(ISNUMBER(I45),I17-I45,"n.m.") -> 0.033775954 | J46: =IF(ISNUMBER(J45),J17-J45,"n.m.") -> 0.043616944 | ... O46: =IF(ISNUMBER(O45),O17-O45,"n.m.") -> 0.029770567 | P46: Positive = above breakeven
A47: Breakeven load factor = (direct flight costs [+ fixed route costs]) / (available seats x (fare - variable cost per passenger)), holding fare, completion and unit costs at that period's values. Values above 100% mean breakeven is not reachable on current capacity. 'n.m.' = not meaningful (fare does not cover variable cost per passenger).
A49: E. Model Integrity Checks
A50: Check | C50: Result | D50: What it tests
A51: Scenario selector is valid | C51: =IF(ISNUMBER(Assumptions!$C$6),"PASS","FAIL") -> PASS | D51: Active scenario name matches Base, Upside or Downside.
A52: Input load factors within 0%-100% (all scenarios) | C52: =IF(AND(MIN(Assumptions!$C$21:$E$21)>=0,MAX(Assumptions!$C$21:$E$21)<=1),"PASS","FAIL") -> PASS | D52: Base/Upside/Downside Month 1 load factor inputs.
A53: Input completion rates within 0%-100% (all scenarios) | C53: =IF(AND(MIN(Assumptions!$C$19:$E$19)>=0,MAX(Assumptions!$C$19:$E$19)<=1),"PASS","FAIL") -> PASS | D53: Base/Upside/Downside completion rate inputs.
A54: Modelled monthly load factor within 0%-100% | C54: =IF(AND(MIN($C$17:$N$17)>=0,MAX($C$17:$N$17)<=1),"PASS","FAIL") -> PASS | D54: After demand growth is applied (row is capped at 100%).
A55: Modelled monthly completion rate within 0%-100% | C55: =IF(AND(MIN($C$16:$N$16)>=0,MAX($C$16:$N$16)<=1),"PASS","FAIL") -> PASS | D55: Active case, every month.
A56: Capacity, flights per day and operating days are non-negative | C56: =IF(AND(Assumptions!$C$14>=0,Assumptions!$C$15>=0,Assumptions!$C$16>=0),"PASS","FAIL") -> PASS | D56: Route setup inputs.
A57: Scheduled and completed flights non-negative; completed <= scheduled | C57: =IF(AND(MIN($C$22:$N$22)>=0,MIN($C$23:$N$23)>=0,SUMPRODUCT(($C$23:$N$23>$C$22:$N$22)*1)=0),"PASS","FAIL") -> PASS | D57: Every month.
A58: Passengers flown <= available seats | C58: =IF(SUMPRODUCT(($C$25:$N$25>$C$24:$N$24+0.000001)*1)=0,"PASS","FAIL") -> PASS | D58: Every month.
A59: Cost inputs non-negative (all scenarios) | C59: =IF(MIN(Assumptions!$C$22:$E$24)>=0,"PASS","FAIL") -> PASS | D59: Variable cost per flight, per passenger and fixed costs.
A60: Modelled costs non-negative | C60: =IF(AND(MIN($C$30:$N$30)>=0,MIN($C$31:$N$31)>=0,MIN($C$36:$N$36)>=0),"PASS","FAIL") -> PASS | D60: Every month, after cost growth.
A61: Annual totals equal the sum of the months | C61: =IF(AND(ABS($O$29-SUM($C$29:$N$29))<0.01,ABS($O$32-SUM($C$32:$N$32))<0.01,ABS($O$37-SUM($C$37:$N$37))<0.01),"PASS","FAIL") -> PASS | D61: Revenue, total variable costs, route operating profit.
A62: Revenue reconciles to passengers x average fare, month by month | C62: =IF(ABS($O$29-SUMPRODUCT($C$25:$N$25,$C$28:$N$28))<0.01,"PASS","FAIL") -> PASS | D62: Annual revenue = sum of (monthly passengers x monthly fare).
A63: Variable costs reconcile (flight + passenger = total) | C63: =IF(ABS($O$30+$O$31-$O$32)<0.01,"PASS","FAIL") -> PASS | D63: No double counting of variable costs.
A64: Route P&L reconciles: revenue - variable - fixed = route operating profit | C64: =IF(ABS($O$29-$O$30-$O$31-$O$36-$O$37)<0.01,"PASS","FAIL") -> PASS | D64: Each cost counted exactly once.
A65: Contribution per flight x completed flights = contribution profit | C65: =IF(IF(ISNUMBER($O$35),ABS($O$35*$O$23-$O$33)<0.01,ABS($O$33)<0.01),"PASS","FAIL") -> PASS | D65: Annual (zero flights must mean zero contribution).
A66: Cumulative route operating profit = annual total | C66: =IF(ABS($O$39-$O$37)<0.01,"PASS","FAIL") -> PASS | D66: Month 12 cumulative vs. FY total.
A67: Scenario Comparison (active case) matches Financial Model - revenue | C67: =IF(ABS(INDEX('Scenario Comparison'!$C$23:$E$23,Assumptions!$C$6)-$O$29)<0.01,"PASS","FAIL") -> PASS | D67: Independent scenario engine reconciles to the main model.
A68: Scenario Comparison (active case) matches Financial Model - route operating profit | C68: =IF(ABS(INDEX('Scenario Comparison'!$C$29:$E$29,Assumptions!$C$6)-$O$37)<0.01,"PASS","FAIL") -> PASS | D68: Independent scenario engine reconciles to the main model.
A69: Scenario Comparison (active case) matches Financial Model - passengers | C69: =IF(ABS(INDEX('Scenario Comparison'!$C$20:$E$20,Assumptions!$C$6)-$O$25)<0.01,"PASS","FAIL") -> PASS | D69: Independent scenario engine reconciles to the main model.
A70: OVERALL MODEL STATUS | C70: =IF(COUNTIF($C$51:$C$69,"PASS")=19,"ALL 19 CHECKS PASS","REVIEW: "&(19-COUNTIF($C$51:$C$69,"PASS"))&" CHECK(S) FAILING") -> ALL 19 CHECKS PASS
A72: Months where demand exceeds seat capacity (load factor capped at 100%) | C72: =SUMPRODUCT((Assumptions!$F$21*$C$14:$N$14>1)*1) -> 0 | D72: Information only. Above zero means the demand growth assumption implies more passengers than seats; the excess is not flown or counted as revenue.

Sheet Scenario Comparison
A1: Scenario Comparison - Base / Upside / Downside
A2: All three cases are computed simultaneously in the engine below, independent of the active-scenario selector.
A3: ILLUSTRATIVE PROTOTYPE - all inputs are hypothetical case-study assumptions, not Joby Aviation forecasts, guidance, or company-reported figures.
A5: Metric | B5: Unit | C5: Base | D5: Upside | E5: Downside | F5: Upside vs Base | G5: Downside vs Base | H5: Notes
A6: Key Scenario Assumptions (linked from Assumptions tab)
A7: Flight completion rate | B7: % | C7: =Assumptions!$C$19 -> 0.95 | D7: =Assumptions!$D$19 -> 0.97 | E7: =Assumptions!$E$19 -> 0.9 | F7: =D7-C7 -> 0.02 | G7: =E7-C7 -> -0.05
A8: Average fare (Month 1) | B8: $ / passenger | C8: =Assumptions!$C$20 -> 175 | D8: =Assumptions!$D$20 -> 190 | E8: =Assumptions!$E$20 -> 160 | F8: =D8-C8 -> 15 | G8: =E8-C8 -> -15
A9: Load factor (Month 1) | B9: % of seats | C9: =Assumptions!$C$21 -> 0.6 | D9: =Assumptions!$D$21 -> 0.68 | E9: =Assumptions!$E$21 -> 0.52 | F9: =D9-C9 -> 0.08 | G9: =E9-C9 -> -0.08
A10: Variable cost per completed flight (Month 1) | B10: $ / flight | C10: =Assumptions!$C$22 -> 300 | D10: =Assumptions!$D$22 -> 280 | E10: =Assumptions!$E$22 -> 320 | F10: =D10-C10 -> -20 | G10: =E10-C10 -> 20
A11: Variable cost per passenger (Month 1) | B11: $ / passenger | C11: =Assumptions!$C$23 -> 12 | D11: =Assumptions!$D$23 -> 10 | E11: =Assumptions!$E$23 -> 15 | F11: =D11-C11 -> -2 | G11: =E11-C11 -> 3
A12: Fixed route costs (Month 1) | B12: $ / month | C12: =Assumptions!$C$24 -> 90000 | D12: =Assumptions!$D$24 -> 85000 | E12: =Assumptions!$E$24 -> 100000 | F12: =D12-C12 -> -5000 | G12: =E12-C12 -> 10000
A13: Monthly fare growth | B13: % / month | C13: =Assumptions!$C$27 -> 0 | D13: =Assumptions!$D$27 -> 0.0025 | E13: =Assumptions!$E$27 -> -0.005 | F13: =D13-C13 -> 0.0025 | G13: =E13-C13 -> -0.005
A14: Monthly demand growth | B14: % / month | C14: =Assumptions!$C$28 -> 0.015 | D14: =Assumptions!$D$28 -> 0.02 | E14: =Assumptions!$E$28 -> 0.005 | F14: =D14-C14 -> 0.005 | G14: =E14-C14 -> -0.01
A15: Monthly operating cost growth | B15: % / month | C15: =Assumptions!$C$29 -> 0 | D15: =Assumptions!$D$29 -> -0.0025 | E15: =Assumptions!$E$29 -> 0.005 | F15: =D15-C15 -> -0.0025 | G15: =E15-C15 -> 0.005
A17: Annual Results (12 months)
A18: Scheduled flights | B18: flights | C18: =O57 -> 10752 | D18: =O75 -> 10752 | E18: =O93 -> 10752 | F18: =IF(AND(ISNUMBER(D18),ISNUMBER(C18)),D18-C18,"n.m.") -> 0 | G18: =IF(AND(ISNUMBER(E18),ISNUMBER(C18)),E18-C18,"n.m.") -> 0
A19: Completed flights | B19: flights | C19: =O58 -> 10214.4 | D19: =O76 -> 10429.44 | E19: =O94 -> 9676.8 | F19: =IF(AND(ISNUMBER(D19),ISNUMBER(C19)),D19-C19,"n.m.") -> 215.04 | G19: =IF(AND(ISNUMBER(E19),ISNUMBER(C19)),E19-C19,"n.m.") -> -537.6
A20: Passengers flown | B20: passengers | C20: =O60 -> 26641.63 | D20: =O78 -> 31706.266 | E20: =O96 -> 20690.587 | F20: =IF(AND(ISNUMBER(D20),ISNUMBER(C20)),D20-C20,"n.m.") -> 5064.6359 | G20: =IF(AND(ISNUMBER(E20),ISNUMBER(C20)),E20-C20,"n.m.") -> -5951.0432
A21: Average load factor (weighted) | B21: % of seats | C21: =IF(O59=0,"n.m.",O60/O59) -> 0.65206057 | D21: =IF(O77=0,"n.m.",O78/O77) -> 0.76001842 | E21: =IF(O95=0,"n.m.",O96/O95) -> 0.53454104 | F21: =IF(AND(ISNUMBER(D21),ISNUMBER(C21)),D21-C21,"n.m.") -> 0.10795785 | G21: =IF(AND(ISNUMBER(E21),ISNUMBER(C21)),E21-C21,"n.m.") -> -0.11751954 | H21: Passengers / available seats
A22: Average fare (weighted) | B22: $ / passenger | C22: =IF(O60=0,"n.m.",O61/O60) -> 175 | D22: =IF(O78=0,"n.m.",O79/O78) -> 192.7478 | E22: =IF(O96=0,"n.m.",O97/O96) -> 155.62615 | F22: =IF(AND(ISNUMBER(D22),ISNUMBER(C22)),D22-C22,"n.m.") -> 17.747801 | G22: =IF(AND(ISNUMBER(E22),ISNUMBER(C22)),E22-C22,"n.m.") -> -19.373855 | H22: Revenue / passengers
A23: Annual passenger revenue | B23: $ | C23: =O61 -> 4662285.3 | D23: =O79 -> 6111313 | E23: =O97 -> 3219996.3 | F23: =IF(AND(ISNUMBER(D23),ISNUMBER(C23)),D23-C23,"n.m.") -> 1449027.8 | G23: =IF(AND(ISNUMBER(E23),ISNUMBER(C23)),E23-C23,"n.m.") -> -1442289
A24: Total variable costs | B24: $ | C24: =O64 -> 3384019.6 | D24: =O82 -> 3192977.2 | E24: =O100 -> 3502299.3 | F24: =IF(AND(ISNUMBER(D24),ISNUMBER(C24)),D24-C24,"n.m.") -> -191042.33 | G24: =IF(AND(ISNUMBER(E24),ISNUMBER(C24)),E24-C24,"n.m.") -> 118279.74 | H24: Direct flight + passenger-variable costs
A25: Contribution profit | B25: $ | C25: =O65 -> 1278265.7 | D25: =O83 -> 2918335.8 | E25: =O101 -> -282303.03 | F25: =IF(AND(ISNUMBER(D25),ISNUMBER(C25)),D25-C25,"n.m.") -> 1640070.1 | G25: =IF(AND(ISNUMBER(E25),ISNUMBER(C25)),E25-C25,"n.m.") -> -1560568.7 | H25: Flight-level, before fixed route costs
A26: Contribution margin | B26: % of revenue | C26: =IF(O61=0,"n.m.",O65/O61) -> 0.27417149 | D26: =IF(O79=0,"n.m.",O83/O79) -> 0.47753008 | E26: =IF(O97=0,"n.m.",O101/O97) -> -0.08767185 | F26: =IF(AND(ISNUMBER(D26),ISNUMBER(C26)),D26-C26,"n.m.") -> 0.20335859 | G26: =IF(AND(ISNUMBER(E26),ISNUMBER(C26)),E26-C26,"n.m.") -> -0.36184334
A27: Contribution profit per completed flight | B27: $ / flight | C27: =IF(O58=0,"n.m.",O65/O58) -> 125.14349 | D27: =IF(O76=0,"n.m.",O83/O76) -> 279.81712 | E27: =IF(O94=0,"n.m.",O101/O94) -> -29.17318 | F27: =IF(AND(ISNUMBER(D27),ISNUMBER(C27)),D27-C27,"n.m.") -> 154.67362 | G27: =IF(AND(ISNUMBER(E27),ISNUMBER(C27)),E27-C27,"n.m.") -> -154.31667
A28: Fixed route costs | B28: $ | C28: =O66 -> 1080000 | D28: =O84 -> 1006091.2 | E28: =O102 -> 1233556.2 | F28: =IF(AND(ISNUMBER(D28),ISNUMBER(C28)),D28-C28,"n.m.") -> -73908.78 | G28: =IF(AND(ISNUMBER(E28),ISNUMBER(C28)),E28-C28,"n.m.") -> 153556.24
A29: Route operating profit / (loss) | B29: $ | C29: =O67 -> 198265.69 | D29: =O85 -> 1912244.6 | E29: =O103 -> -1515859.3 | F29: =IF(AND(ISNUMBER(D29),ISNUMBER(C29)),D29-C29,"n.m.") -> 1713978.9 | G29: =IF(AND(ISNUMBER(E29),ISNUMBER(C29)),E29-C29,"n.m.") -> -1714125 | H29: After route fixed costs; not EBITDA
A30: Route operating margin | B30: % of revenue | C30: =IF(O61=0,"n.m.",O67/O61) -> 0.042525431 | D30: =IF(O79=0,"n.m.",O85/O79) -> 0.31290241 | E30: =IF(O97=0,"n.m.",O103/O97) -> -0.47076429 | F30: =IF(AND(ISNUMBER(D30),ISNUMBER(C30)),D30-C30,"n.m.") -> 0.27037698 | G30: =IF(AND(ISNUMBER(E30),ISNUMBER(C30)),E30-C30,"n.m.") -> -0.51328972
A31: Breakeven load factor - flight level | B31: % of seats | C31: =IF(O68>0,O62/O68,"n.m.") -> 0.4601227 | D31: =IF(O86>0,O80/O86,"n.m.") -> 0.37777092 | E31: =IF(O104>0,O98/O104,"n.m.") -> 0.58634786 | F31: =IF(AND(ISNUMBER(D31),ISNUMBER(C31)),D31-C31,"n.m.") -> -0.08235178 | G31: =IF(AND(ISNUMBER(E31),ISNUMBER(C31)),E31-C31,"n.m.") -> 0.12622516 | H31: Load factor at which contribution = 0
A32: Breakeven load factor - route | B32: % of seats | C32: =IF(O68>0,(O62+O66)/O68,"n.m.") -> 0.62229 | D32: =IF(O86>0,(O80+O84)/O86,"n.m.") -> 0.509721 | E32: =IF(O104>0,(O98+O102)/O104,"n.m.") -> 0.8135722 | F32: =IF(AND(ISNUMBER(D32),ISNUMBER(C32)),D32-C32,"n.m.") -> -0.112569 | G32: =IF(AND(ISNUMBER(E32),ISNUMBER(C32)),E32-C32,"n.m.") -> 0.19128219 | H32: Load factor at which route operating profit = 0
A33: Months with positive route operating profit | B33: months | C33: =COUNTIF(C67:N67,">0") -> 9 | D33: =COUNTIF(C85:N85,">0") -> 12 | E33: =COUNTIF(C103:N103,">0") -> 0 | F33: =IF(AND(ISNUMBER(D33),ISNUMBER(C33)),D33-C33,"n.m.") -> 3 | G33: =IF(AND(ISNUMBER(E33),ISNUMBER(C33)),E33-C33,"n.m.") -> -9
A35: Scenario Definitions
A36: Base | B36: Steady launch: 95% completion, $175 fare, 60% load factor building ~1.5%/month, flat unit costs.
A37: Upside | B37: Strong adoption: higher fare and load factor, faster demand ramp, better reliability and modest cost efficiencies.
A38: Downside | B38: Soft launch: discounted fares, weaker demand, more weather/technical cancellations and cost inflation.
A40: Variance columns show Upside/Downside minus Base (percentage rows are differences in percentage points). Scenario values are illustrative.
A50: Scenario Calculation Engine (monthly; same logic as the Financial Model tab)
A52: Base case | B52: Unit | C52: Month 1 | D52: Month 2 | E52: Month 3 | F52: Month 4 | G52: Month 5 | H52: Month 6 | I52: Month 7 | J52: Month 8 | K52: Month 9 | L52: Month 10 | M52: Month 11 | N52: Month 12 | O52: FY Total
A53: Month index | C53: 1 | D53: =C53+1 -> 2 | E53: =D53+1 -> 3 | F53: =E53+1 -> 4 | G53: =F53+1 -> 5 | H53: =G53+1 -> 6 | I53: =H53+1 -> 7 | J53: =I53+1 -> 8 | K53: =J53+1 -> 9 | ... N53: =M53+1 -> 12
A54: Average fare | B54: $ / passenger | C54: =Assumptions!$C$20*(1+Assumptions!$C$27)^(C$53-1) -> 175 | D54: =Assumptions!$C$20*(1+Assumptions!$C$27)^(D$53-1) -> 175 | E54: =Assumptions!$C$20*(1+Assumptions!$C$27)^(E$53-1) -> 175 | F54: =Assumptions!$C$20*(1+Assumptions!$C$27)^(F$53-1) -> 175 | G54: =Assumptions!$C$20*(1+Assumptions!$C$27)^(G$53-1) -> 175 | H54: =Assumptions!$C$20*(1+Assumptions!$C$27)^(H$53-1) -> 175 | I54: =Assumptions!$C$20*(1+Assumptions!$C$27)^(I$53-1) -> 175 | J54: =Assumptions!$C$20*(1+Assumptions!$C$27)^(J$53-1) -> 175 | ... N54: =Assumptions!$C$20*(1+Assumptions!$C$27)^(N$53-1) -> 175
A55: Passenger load factor | B55: % of seats | C55: =MIN(1,MAX(0,Assumptions!$C$21*(1+Assumptions!$C$28)^(C$53-1))) -> 0.6 | D55: =MIN(1,MAX(0,Assumptions!$C$21*(1+Assumptions!$C$28)^(D$53-1))) -> 0.609 | E55: =MIN(1,MAX(0,Assumptions!$C$21*(1+Assumptions!$C$28)^(E$53-1))) -> 0.618135 | F55: =MIN(1,MAX(0,Assumptions!$C$21*(1+Assumptions!$C$28)^(F$53-1))) -> 0.62740703 | G55: =MIN(1,MAX(0,Assumptions!$C$21*(1+Assumptions!$C$28)^(G$53-1))) -> 0.63681813 | H55: =MIN(1,MAX(0,Assumptions!$C$21*(1+Assumptions!$C$28)^(H$53-1))) -> 0.6463704 | I55: =MIN(1,MAX(0,Assumptions!$C$21*(1+Assumptions!$C$28)^(I$53-1))) -> 0.65606596 | J55: =MIN(1,MAX(0,Assumptions!$C$21*(1+Assumptions!$C$28)^(J$53-1))) -> 0.66590695 | ... N55: =MIN(1,MAX(0,Assumptions!$C$21*(1+Assumptions!$C$28)^(N$53-1))) -> 0.70676936
A56: Operating cost growth index | B56: index | C56: =(1+Assumptions!$C$29)^(C$53-1) -> 1 | D56: =(1+Assumptions!$C$29)^(D$53-1) -> 1 | E56: =(1+Assumptions!$C$29)^(E$53-1) -> 1 | F56: =(1+Assumptions!$C$29)^(F$53-1) -> 1 | G56: =(1+Assumptions!$C$29)^(G$53-1) -> 1 | H56: =(1+Assumptions!$C$29)^(H$53-1) -> 1 | I56: =(1+Assumptions!$C$29)^(I$53-1) -> 1 | J56: =(1+Assumptions!$C$29)^(J$53-1) -> 1 | ... N56: =(1+Assumptions!$C$29)^(N$53-1) -> 1
A57: Scheduled flights | B57: flights | C57: =Assumptions!$F$16*Assumptions!$F$15 -> 896 | D57: =Assumptions!$F$16*Assumptions!$F$15 -> 896 | E57: =Assumptions!$F$16*Assumptions!$F$15 -> 896 | F57: =Assumptions!$F$16*Assumptions!$F$15 -> 896 | G57: =Assumptions!$F$16*Assumptions!$F$15 -> 896 | H57: =Assumptions!$F$16*Assumptions!$F$15 -> 896 | I57: =Assumptions!$F$16*Assumptions!$F$15 -> 896 | J57: =Assumptions!$F$16*Assumptions!$F$15 -> 896 | ... N57: =Assumptions!$F$16*Assumptions!$F$15 -> 896 | O57: =SUM(C57:N57) -> 10752
A58: Completed flights | B58: flights | C58: =C57*Assumptions!$C$19 -> 851.2 | D58: =D57*Assumptions!$C$19 -> 851.2 | E58: =E57*Assumptions!$C$19 -> 851.2 | F58: =F57*Assumptions!$C$19 -> 851.2 | G58: =G57*Assumptions!$C$19 -> 851.2 | H58: =H57*Assumptions!$C$19 -> 851.2 | I58: =I57*Assumptions!$C$19 -> 851.2 | J58: =J57*Assumptions!$C$19 -> 851.2 | ... N58: =N57*Assumptions!$C$19 -> 851.2 | O58: =SUM(C58:N58) -> 10214.4
A59: Available passenger seats | B59: seats | C59: =C58*Assumptions!$F$14 -> 3404.8 | D59: =D58*Assumptions!$F$14 -> 3404.8 | E59: =E58*Assumptions!$F$14 -> 3404.8 | F59: =F58*Assumptions!$F$14 -> 3404.8 | G59: =G58*Assumptions!$F$14 -> 3404.8 | H59: =H58*Assumptions!$F$14 -> 3404.8 | I59: =I58*Assumptions!$F$14 -> 3404.8 | J59: =J58*Assumptions!$F$14 -> 3404.8 | ... N59: =N58*Assumptions!$F$14 -> 3404.8 | O59: =SUM(C59:N59) -> 40857.6
A60: Passengers flown | B60: passengers | C60: =C59*C55 -> 2042.88 | D60: =D59*D55 -> 2073.5232 | E60: =E59*E55 -> 2104.626 | F60: =F59*F55 -> 2136.1954 | G60: =G59*G55 -> 2168.2384 | H60: =H59*H55 -> 2200.7619 | I60: =I59*I55 -> 2233.7734 | J60: =J59*J55 -> 2267.28 | ... N60: =N59*N55 -> 2406.4083 | O60: =SUM(C60:N60) -> 26641.63
A61: Passenger revenue | B61: $ | C61: =C60*C54 -> 357504 | D61: =D60*D54 -> 362866.56 | E61: =E60*E54 -> 368309.56 | F61: =F60*F54 -> 373834.2 | G61: =G60*G54 -> 379441.71 | H61: =H60*H54 -> 385133.34 | I61: =I60*I54 -> 390910.34 | J61: =J60*J54 -> 396774 | ... N61: =N60*N54 -> 421121.46 | O61: =SUM(C61:N61) -> 4662285.3
A62: Direct flight operating costs | B62: $ | C62: =C58*Assumptions!$C$22*C56 -> 255360 | D62: =D58*Assumptions!$C$22*D56 -> 255360 | E62: =E58*Assumptions!$C$22*E56 -> 255360 | F62: =F58*Assumptions!$C$22*F56 -> 255360 | G62: =G58*Assumptions!$C$22*G56 -> 255360 | H62: =H58*Assumptions!$C$22*H56 -> 255360 | I62: =I58*Assumptions!$C$22*I56 -> 255360 | J62: =J58*Assumptions!$C$22*J56 -> 255360 | ... N62: =N58*Assumptions!$C$22*N56 -> 255360 | O62: =SUM(C62:N62) -> 3064320
A63: Passenger-variable costs | B63: $ | C63: =C60*Assumptions!$C$23*C56 -> 24514.56 | D63: =D60*Assumptions!$C$23*D56 -> 24882.278 | E63: =E60*Assumptions!$C$23*E56 -> 25255.513 | F63: =F60*Assumptions!$C$23*F56 -> 25634.345 | G63: =G60*Assumptions!$C$23*G56 -> 26018.86 | H63: =H60*Assumptions!$C$23*H56 -> 26409.143 | I63: =I60*Assumptions!$C$23*I56 -> 26805.281 | J63: =J60*Assumptions!$C$23*J56 -> 27207.36 | ... N63: =N60*Assumptions!$C$23*N56 -> 28876.9 | O63: =SUM(C63:N63) -> 319699.56
A64: Total variable costs | B64: $ | C64: =C62+C63 -> 279874.56 | D64: =D62+D63 -> 280242.28 | E64: =E62+E63 -> 280615.51 | F64: =F62+F63 -> 280994.35 | G64: =G62+G63 -> 281378.86 | H64: =H62+H63 -> 281769.14 | I64: =I62+I63 -> 282165.28 | J64: =J62+J63 -> 282567.36 | ... N64: =N62+N63 -> 284236.9 | O64: =SUM(C64:N64) -> 3384019.6
A65: Contribution profit | B65: $ | C65: =C61-C64 -> 77629.44 | D65: =D61-D64 -> 82624.282 | E65: =E61-E64 -> 87694.046 | F65: =F61-F64 -> 92839.857 | G65: =G61-G64 -> 98062.854 | H65: =H61-H64 -> 103364.2 | I65: =I61-I64 -> 108745.06 | J65: =J61-J64 -> 114206.64 | ... N65: =N61-N64 -> 136884.56 | O65: =SUM(C65:N65) -> 1278265.7
A66: Fixed route costs | B66: $ | C66: =Assumptions!$C$24*C56 -> 90000 | D66: =Assumptions!$C$24*D56 -> 90000 | E66: =Assumptions!$C$24*E56 -> 90000 | F66: =Assumptions!$C$24*F56 -> 90000 | G66: =Assumptions!$C$24*G56 -> 90000 | H66: =Assumptions!$C$24*H56 -> 90000 | I66: =Assumptions!$C$24*I56 -> 90000 | J66: =Assumptions!$C$24*J56 -> 90000 | ... N66: =Assumptions!$C$24*N56 -> 90000 | O66: =SUM(C66:N66) -> 1080000
A67: Route operating profit / (loss) | B67: $ | C67: =C65-C66 -> -12370.56 | D67: =D65-D66 -> -7375.7184 | E67: =E65-E66 -> -2305.9542 | F67: =F65-F66 -> 2839.8565 | G67: =G65-G66 -> 8062.8544 | H67: =H65-H66 -> 13364.197 | I67: =I65-I66 -> 18745.06 | J67: =J65-J66 -> 24206.636 | ... N67: =N65-N66 -> 46884.557 | O67: =SUM(C67:N67) -> 198265.69
A68: Passenger margin at 100% load factor | B68: $ | C68: =C59*(C54-Assumptions!$C$23*C56) -> 554982.4 | D68: =D59*(D54-Assumptions!$C$23*D56) -> 554982.4 | E68: =E59*(E54-Assumptions!$C$23*E56) -> 554982.4 | F68: =F59*(F54-Assumptions!$C$23*F56) -> 554982.4 | G68: =G59*(G54-Assumptions!$C$23*G56) -> 554982.4 | H68: =H59*(H54-Assumptions!$C$23*H56) -> 554982.4 | I68: =I59*(I54-Assumptions!$C$23*I56) -> 554982.4 | J68: =J59*(J54-Assumptions!$C$23*J56) -> 554982.4 | ... N68: =N59*(N54-Assumptions!$C$23*N56) -> 554982.4 | O68: =SUM(C68:N68) -> 6659788.8
A70: Upside case | B70: Unit | C70: Month 1 | D70: Month 2 | E70: Month 3 | F70: Month 4 | G70: Month 5 | H70: Month 6 | I70: Month 7 | J70: Month 8 | K70: Month 9 | L70: Month 10 | M70: Month 11 | N70: Month 12 | O70: FY Total
A71: Month index | C71: 1 | D71: =C71+1 -> 2 | E71: =D71+1 -> 3 | F71: =E71+1 -> 4 | G71: =F71+1 -> 5 | H71: =G71+1 -> 6 | I71: =H71+1 -> 7 | J71: =I71+1 -> 8 | K71: =J71+1 -> 9 | ... N71: =M71+1 -> 12
A72: Average fare | B72: $ / passenger | C72: =Assumptions!$D$20*(1+Assumptions!$D$27)^(C$71-1) -> 190 | D72: =Assumptions!$D$20*(1+Assumptions!$D$27)^(D$71-1) -> 190.475 | E72: =Assumptions!$D$20*(1+Assumptions!$D$27)^(E$71-1) -> 190.95119 | F72: =Assumptions!$D$20*(1+Assumptions!$D$27)^(F$71-1) -> 191.42857 | G72: =Assumptions!$D$20*(1+Assumptions!$D$27)^(G$71-1) -> 191.90714 | H72: =Assumptions!$D$20*(1+Assumptions!$D$27)^(H$71-1) -> 192.3869 | I72: =Assumptions!$D$20*(1+Assumptions!$D$27)^(I$71-1) -> 192.86787 | J72: =Assumptions!$D$20*(1+Assumptions!$D$27)^(J$71-1) -> 193.35004 | ... N72: =Assumptions!$D$20*(1+Assumptions!$D$27)^(N$71-1) -> 195.2908
A73: Passenger load factor | B73: % of seats | C73: =MIN(1,MAX(0,Assumptions!$D$21*(1+Assumptions!$D$28)^(C$71-1))) -> 0.68 | D73: =MIN(1,MAX(0,Assumptions!$D$21*(1+Assumptions!$D$28)^(D$71-1))) -> 0.6936 | E73: =MIN(1,MAX(0,Assumptions!$D$21*(1+Assumptions!$D$28)^(E$71-1))) -> 0.707472 | F73: =MIN(1,MAX(0,Assumptions!$D$21*(1+Assumptions!$D$28)^(F$71-1))) -> 0.72162144 | G73: =MIN(1,MAX(0,Assumptions!$D$21*(1+Assumptions!$D$28)^(G$71-1))) -> 0.73605387 | H73: =MIN(1,MAX(0,Assumptions!$D$21*(1+Assumptions!$D$28)^(H$71-1))) -> 0.75077495 | I73: =MIN(1,MAX(0,Assumptions!$D$21*(1+Assumptions!$D$28)^(I$71-1))) -> 0.76579045 | J73: =MIN(1,MAX(0,Assumptions!$D$21*(1+Assumptions!$D$28)^(J$71-1))) -> 0.78110625 | ... N73: =MIN(1,MAX(0,Assumptions!$D$21*(1+Assumptions!$D$28)^(N$71-1))) -> 0.84549453
A74: Operating cost growth index | B74: index | C74: =(1+Assumptions!$D$29)^(C$71-1) -> 1 | D74: =(1+Assumptions!$D$29)^(D$71-1) -> 0.9975 | E74: =(1+Assumptions!$D$29)^(E$71-1) -> 0.99500625 | F74: =(1+Assumptions!$D$29)^(F$71-1) -> 0.99251873 | G74: =(1+Assumptions!$D$29)^(G$71-1) -> 0.99003744 | H74: =(1+Assumptions!$D$29)^(H$71-1) -> 0.98756234 | I74: =(1+Assumptions!$D$29)^(I$71-1) -> 0.98509344 | J74: =(1+Assumptions!$D$29)^(J$71-1) -> 0.9826307 | ... N74: =(1+Assumptions!$D$29)^(N$71-1) -> 0.97284118
A75: Scheduled flights | B75: flights | C75: =Assumptions!$F$16*Assumptions!$F$15 -> 896 | D75: =Assumptions!$F$16*Assumptions!$F$15 -> 896 | E75: =Assumptions!$F$16*Assumptions!$F$15 -> 896 | F75: =Assumptions!$F$16*Assumptions!$F$15 -> 896 | G75: =Assumptions!$F$16*Assumptions!$F$15 -> 896 | H75: =Assumptions!$F$16*Assumptions!$F$15 -> 896 | I75: =Assumptions!$F$16*Assumptions!$F$15 -> 896 | J75: =Assumptions!$F$16*Assumptions!$F$15 -> 896 | ... N75: =Assumptions!$F$16*Assumptions!$F$15 -> 896 | O75: =SUM(C75:N75) -> 10752
A76: Completed flights | B76: flights | C76: =C75*Assumptions!$D$19 -> 869.12 | D76: =D75*Assumptions!$D$19 -> 869.12 | E76: =E75*Assumptions!$D$19 -> 869.12 | F76: =F75*Assumptions!$D$19 -> 869.12 | G76: =G75*Assumptions!$D$19 -> 869.12 | H76: =H75*Assumptions!$D$19 -> 869.12 | I76: =I75*Assumptions!$D$19 -> 869.12 | J76: =J75*Assumptions!$D$19 -> 869.12 | ... N76: =N75*Assumptions!$D$19 -> 869.12 | O76: =SUM(C76:N76) -> 10429.44
A77: Available passenger seats | B77: seats | C77: =C76*Assumptions!$F$14 -> 3476.48 | D77: =D76*Assumptions!$F$14 -> 3476.48 | E77: =E76*Assumptions!$F$14 -> 3476.48 | F77: =F76*Assumptions!$F$14 -> 3476.48 | G77: =G76*Assumptions!$F$14 -> 3476.48 | H77: =H76*Assumptions!$F$14 -> 3476.48 | I77: =I76*Assumptions!$F$14 -> 3476.48 | J77: =J76*Assumptions!$F$14 -> 3476.48 | ... N77: =N76*Assumptions!$F$14 -> 3476.48 | O77: =SUM(C77:N77) -> 41717.76
A78: Passengers flown | B78: passengers | C78: =C77*C73 -> 2364.0064 | D78: =D77*D73 -> 2411.2865 | E78: =E77*E73 -> 2459.5123 | F78: =F77*F73 -> 2508.7025 | G78: =G77*G73 -> 2558.8766 | H78: =H77*H73 -> 2610.0541 | I78: =I77*I73 -> 2662.2552 | J78: =J77*J73 -> 2715.5003 | ... N78: =N77*N73 -> 2939.3448 | O78: =SUM(C78:N78) -> 31706.266
A79: Passenger revenue | B79: $ | C79: =C78*C72 -> 449161.22 | D79: =D78*D72 -> 459289.8 | E79: =E78*E72 -> 469646.79 | F79: =F78*F72 -> 480237.32 | G79: =G78*G72 -> 491066.67 | H79: =H78*H72 -> 502140.23 | I79: =I78*I72 -> 513463.49 | J79: =J78*J72 -> 525042.09 | ... N79: =N78*N72 -> 574027.02 | O79: =SUM(C79:N79) -> 6111313
A80: Direct flight operating costs | B80: $ | C80: =C76*Assumptions!$D$22*C74 -> 243353.6 | D80: =D76*Assumptions!$D$22*D74 -> 242745.22 | E80: =E76*Assumptions!$D$22*E74 -> 242138.35 | F80: =F76*Assumptions!$D$22*F74 -> 241533.01 | G80: =G76*Assumptions!$D$22*G74 -> 240929.17 | H80: =H76*Assumptions!$D$22*H74 -> 240326.85 | I80: =I76*Assumptions!$D$22*I74 -> 239726.03 | J80: =J76*Assumptions!$D$22*J74 -> 239126.72 | ... N80: =N76*Assumptions!$D$22*N74 -> 236744.4 | O80: =SUM(C80:N80) -> 2880422.6
A81: Passenger-variable costs | B81: $ | C81: =C78*Assumptions!$D$23*C74 -> 23640.064 | D81: =D78*Assumptions!$D$23*D74 -> 24052.583 | E81: =E78*Assumptions!$D$23*E74 -> 24472.301 | F81: =F78*Assumptions!$D$23*F74 -> 24899.342 | G81: =G78*Assumptions!$D$23*G74 -> 25333.836 | H81: =H78*Assumptions!$D$23*H74 -> 25775.911 | I81: =I78*Assumptions!$D$23*I74 -> 26225.701 | J81: =J78*Assumptions!$D$23*J74 -> 26683.339 | ... N81: =N78*Assumptions!$D$23*N74 -> 28595.157 | O81: =SUM(C81:N81) -> 312554.64
A82: Total variable costs | B82: $ | C82: =C80+C81 -> 266993.66 | D82: =D80+D81 -> 266797.8 | E82: =E80+E81 -> 266610.65 | F82: =F80+F81 -> 266432.35 | G82: =G80+G81 -> 266263.01 | H82: =H80+H81 -> 266102.76 | I82: =I80+I81 -> 265951.74 | J82: =J80+J81 -> 265810.06 | ... N82: =N80+N81 -> 265339.56 | O82: =SUM(C82:N82) -> 3192977.2
A83: Contribution profit | B83: $ | C83: =C79-C82 -> 182167.55 | D83: =D79-D82 -> 192492 | E83: =E79-E82 -> 203036.13 | F83: =F79-F82 -> 213804.97 | G83: =G79-G82 -> 224803.66 | H83: =H79-H82 -> 236037.46 | I83: =I79-I82 -> 247511.75 | J83: =J79-J82 -> 259232.03 | ... N83: =N79-N82 -> 308687.45 | O83: =SUM(C83:N83) -> 2918335.8
A84: Fixed route costs | B84: $ | C84: =Assumptions!$D$24*C74 -> 85000 | D84: =Assumptions!$D$24*D74 -> 84787.5 | E84: =Assumptions!$D$24*E74 -> 84575.531 | F84: =Assumptions!$D$24*F74 -> 84364.092 | G84: =Assumptions!$D$24*G74 -> 84153.182 | H84: =Assumptions!$D$24*H74 -> 83942.799 | I84: =Assumptions!$D$24*I74 -> 83732.942 | J84: =Assumptions!$D$24*J74 -> 83523.61 | ... N84: =Assumptions!$D$24*N74 -> 82691.501 | O84: =SUM(C84:N84) -> 1006091.2
A85: Route operating profit / (loss) | B85: $ | C85: =C83-C84 -> 97167.552 | D85: =D83-D84 -> 107704.5 | E85: =E83-E84 -> 118460.6 | F85: =F83-F84 -> 129440.88 | G85: =G83-G84 -> 140650.48 | H85: =H83-H84 -> 152094.66 | I85: =I83-I84 -> 163778.81 | J85: =J83-J84 -> 175708.42 | ... N85: =N83-N84 -> 225995.95 | O85: =SUM(C85:N85) -> 1912244.6
A86: Passenger margin at 100% load factor | B86: $ | C86: =C77*(C72-Assumptions!$D$23*C74) -> 625766.4 | D86: =D77*(D72-Assumptions!$D$23*D74) -> 627504.64 | E86: =E77*(E72-Assumptions!$D$23*E74) -> 629246.79 | F86: =F77*(F72-Assumptions!$D$23*F74) -> 630992.86 | G86: =G77*(G72-Assumptions!$D$23*G74) -> 632742.87 | H86: =H77*(H72-Assumptions!$D$23*H74) -> 634496.82 | I86: =I77*(I72-Assumptions!$D$23*I74) -> 636254.72 | J86: =J77*(J72-Assumptions!$D$23*J74) -> 638016.59 | ... N86: =N77*(N72-Assumptions!$D$23*N74) -> 645103.95 | O86: =SUM(C86:N86) -> 7624786.5
A88: Downside case | B88: Unit | C88: Month 1 | D88: Month 2 | E88: Month 3 | F88: Month 4 | G88: Month 5 | H88: Month 6 | I88: Month 7 | J88: Month 8 | K88: Month 9 | L88: Month 10 | M88: Month 11 | N88: Month 12 | O88: FY Total
A89: Month index | C89: 1 | D89: =C89+1 -> 2 | E89: =D89+1 -> 3 | F89: =E89+1 -> 4 | G89: =F89+1 -> 5 | H89: =G89+1 -> 6 | I89: =H89+1 -> 7 | J89: =I89+1 -> 8 | K89: =J89+1 -> 9 | ... N89: =M89+1 -> 12
A90: Average fare | B90: $ / passenger | C90: =Assumptions!$E$20*(1+Assumptions!$E$27)^(C$89-1) -> 160 | D90: =Assumptions!$E$20*(1+Assumptions!$E$27)^(D$89-1) -> 159.2 | E90: =Assumptions!$E$20*(1+Assumptions!$E$27)^(E$89-1) -> 158.404 | F90: =Assumptions!$E$20*(1+Assumptions!$E$27)^(F$89-1) -> 157.61198 | G90: =Assumptions!$E$20*(1+Assumptions!$E$27)^(G$89-1) -> 156.82392 | H90: =Assumptions!$E$20*(1+Assumptions!$E$27)^(H$89-1) -> 156.0398 | I90: =Assumptions!$E$20*(1+Assumptions!$E$27)^(I$89-1) -> 155.2596 | J90: =Assumptions!$E$20*(1+Assumptions!$E$27)^(J$89-1) -> 154.4833 | ... N90: =Assumptions!$E$20*(1+Assumptions!$E$27)^(N$89-1) -> 151.41673
A91: Passenger load factor | B91: % of seats | C91: =MIN(1,MAX(0,Assumptions!$E$21*(1+Assumptions!$E$28)^(C$89-1))) -> 0.52 | D91: =MIN(1,MAX(0,Assumptions!$E$21*(1+Assumptions!$E$28)^(D$89-1))) -> 0.5226 | E91: =MIN(1,MAX(0,Assumptions!$E$21*(1+Assumptions!$E$28)^(E$89-1))) -> 0.525213 | F91: =MIN(1,MAX(0,Assumptions!$E$21*(1+Assumptions!$E$28)^(F$89-1))) -> 0.52783906 | G91: =MIN(1,MAX(0,Assumptions!$E$21*(1+Assumptions!$E$28)^(G$89-1))) -> 0.53047826 | H91: =MIN(1,MAX(0,Assumptions!$E$21*(1+Assumptions!$E$28)^(H$89-1))) -> 0.53313065 | I91: =MIN(1,MAX(0,Assumptions!$E$21*(1+Assumptions!$E$28)^(I$89-1))) -> 0.5357963 | J91: =MIN(1,MAX(0,Assumptions!$E$21*(1+Assumptions!$E$28)^(J$89-1))) -> 0.53847529 | ... N91: =MIN(1,MAX(0,Assumptions!$E$21*(1+Assumptions!$E$28)^(N$89-1))) -> 0.54932583
A92: Operating cost growth index | B92: index | C92: =(1+Assumptions!$E$29)^(C$89-1) -> 1 | D92: =(1+Assumptions!$E$29)^(D$89-1) -> 1.005 | E92: =(1+Assumptions!$E$29)^(E$89-1) -> 1.010025 | F92: =(1+Assumptions!$E$29)^(F$89-1) -> 1.0150751 | G92: =(1+Assumptions!$E$29)^(G$89-1) -> 1.0201505 | H92: =(1+Assumptions!$E$29)^(H$89-1) -> 1.0252513 | I92: =(1+Assumptions!$E$29)^(I$89-1) -> 1.0303775 | J92: =(1+Assumptions!$E$29)^(J$89-1) -> 1.0355294 | ... N92: =(1+Assumptions!$E$29)^(N$89-1) -> 1.0563958
A93: Scheduled flights | B93: flights | C93: =Assumptions!$F$16*Assumptions!$F$15 -> 896 | D93: =Assumptions!$F$16*Assumptions!$F$15 -> 896 | E93: =Assumptions!$F$16*Assumptions!$F$15 -> 896 | F93: =Assumptions!$F$16*Assumptions!$F$15 -> 896 | G93: =Assumptions!$F$16*Assumptions!$F$15 -> 896 | H93: =Assumptions!$F$16*Assumptions!$F$15 -> 896 | I93: =Assumptions!$F$16*Assumptions!$F$15 -> 896 | J93: =Assumptions!$F$16*Assumptions!$F$15 -> 896 | ... N93: =Assumptions!$F$16*Assumptions!$F$15 -> 896 | O93: =SUM(C93:N93) -> 10752
A94: Completed flights | B94: flights | C94: =C93*Assumptions!$E$19 -> 806.4 | D94: =D93*Assumptions!$E$19 -> 806.4 | E94: =E93*Assumptions!$E$19 -> 806.4 | F94: =F93*Assumptions!$E$19 -> 806.4 | G94: =G93*Assumptions!$E$19 -> 806.4 | H94: =H93*Assumptions!$E$19 -> 806.4 | I94: =I93*Assumptions!$E$19 -> 806.4 | J94: =J93*Assumptions!$E$19 -> 806.4 | ... N94: =N93*Assumptions!$E$19 -> 806.4 | O94: =SUM(C94:N94) -> 9676.8
A95: Available passenger seats | B95: seats | C95: =C94*Assumptions!$F$14 -> 3225.6 | D95: =D94*Assumptions!$F$14 -> 3225.6 | E95: =E94*Assumptions!$F$14 -> 3225.6 | F95: =F94*Assumptions!$F$14 -> 3225.6 | G95: =G94*Assumptions!$F$14 -> 3225.6 | H95: =H94*Assumptions!$F$14 -> 3225.6 | I95: =I94*Assumptions!$F$14 -> 3225.6 | J95: =J94*Assumptions!$F$14 -> 3225.6 | ... N95: =N94*Assumptions!$F$14 -> 3225.6 | O95: =SUM(C95:N95) -> 38707.2
A96: Passengers flown | B96: passengers | C96: =C95*C91 -> 1677.312 | D96: =D95*D91 -> 1685.6986 | E96: =E95*E91 -> 1694.1271 | F96: =F95*F91 -> 1702.5977 | G96: =G95*G91 -> 1711.1107 | H96: =H95*H91 -> 1719.6662 | I96: =I95*I91 -> 1728.2646 | J96: =J95*J91 -> 1736.9059 | ... N96: =N95*N91 -> 1771.9054 | O96: =SUM(C96:N96) -> 20690.587
A97: Passenger revenue | B97: $ | C97: =C96*C90 -> 268369.92 | D97: =D96*D90 -> 268363.21 | E97: =E96*E90 -> 268356.5 | F97: =F96*F90 -> 268349.79 | G97: =G96*G90 -> 268343.08 | H97: =H96*H90 -> 268336.38 | I97: =I96*I90 -> 268329.67 | J97: =J96*J90 -> 268322.96 | ... N97: =N96*N90 -> 268296.13 | O97: =SUM(C97:N97) -> 3219996.3
A98: Direct flight operating costs | B98: $ | C98: =C94*Assumptions!$E$22*C92 -> 258048 | D98: =D94*Assumptions!$E$22*D92 -> 259338.24 | E98: =E94*Assumptions!$E$22*E92 -> 260634.93 | F98: =F94*Assumptions!$E$22*F92 -> 261938.11 | G98: =G94*Assumptions!$E$22*G92 -> 263247.8 | H98: =H94*Assumptions!$E$22*H92 -> 264564.04 | I98: =I94*Assumptions!$E$22*I92 -> 265886.86 | J98: =J94*Assumptions!$E$22*J92 -> 267216.29 | ... N98: =N94*Assumptions!$E$22*N92 -> 272600.83 | O98: =SUM(C98:N98) -> 3183167.2
A99: Passenger-variable costs | B99: $ | C99: =C96*Assumptions!$E$23*C92 -> 25159.68 | D99: =D96*Assumptions!$E$23*D92 -> 25411.906 | E99: =E96*Assumptions!$E$23*E92 -> 25666.66 | F99: =F96*Assumptions!$E$23*F92 -> 25923.968 | G99: =G96*Assumptions!$E$23*G92 -> 26183.856 | H99: =H96*Assumptions!$E$23*H92 -> 26446.349 | I99: =I96*Assumptions!$E$23*I92 -> 26711.474 | J99: =J96*Assumptions!$E$23*J92 -> 26979.257 | ... N99: =N96*Assumptions!$E$23*N92 -> 28077.502 | O99: =SUM(C99:N99) -> 319132.1
A100: Total variable costs | B100: $ | C100: =C98+C99 -> 283207.68 | D100: =D98+D99 -> 284750.15 | E100: =E98+E99 -> 286301.59 | F100: =F98+F99 -> 287862.07 | G100: =G98+G99 -> 289431.65 | H100: =H98+H99 -> 291010.38 | I100: =I98+I99 -> 292598.33 | J100: =J98+J99 -> 294195.55 | ... N100: =N98+N99 -> 300678.33 | O100: =SUM(C100:N100) -> 3502299.3
A101: Contribution profit | B101: $ | C101: =C97-C100 -> -14837.76 | D101: =D97-D100 -> -16386.935 | E101: =E97-E100 -> -17945.09 | F101: =F97-F100 -> -19512.282 | G101: =G97-G100 -> -21088.569 | H101: =H97-H100 -> -22674.009 | I101: =I97-I100 -> -24268.663 | J101: =J97-J100 -> -25872.588 | ... N101: =N97-N100 -> -32382.207 | O101: =SUM(C101:N101) -> -282303.03
A102: Fixed route costs | B102: $ | C102: =Assumptions!$E$24*C92 -> 100000 | D102: =Assumptions!$E$24*D92 -> 100500 | E102: =Assumptions!$E$24*E92 -> 101002.5 | F102: =Assumptions!$E$24*F92 -> 101507.51 | G102: =Assumptions!$E$24*G92 -> 102015.05 | H102: =Assumptions!$E$24*H92 -> 102525.13 | I102: =Assumptions!$E$24*I92 -> 103037.75 | J102: =Assumptions!$E$24*J92 -> 103552.94 | ... N102: =Assumptions!$E$24*N92 -> 105639.58 | O102: =SUM(C102:N102) -> 1233556.2
A103: Route operating profit / (loss) | B103: $ | C103: =C101-C102 -> -114837.76 | D103: =D101-D102 -> -116886.94 | E103: =E101-E102 -> -118947.59 | F103: =F101-F102 -> -121019.79 | G103: =G101-G102 -> -123103.62 | H103: =H101-H102 -> -125199.13 | I103: =I101-I102 -> -127306.41 | J103: =J101-J102 -> -129425.53 | ... N103: =N101-N102 -> -138021.79 | O103: =SUM(C103:N103) -> -1515859.3
A104: Passenger margin at 100% load factor | B104: $ | C104: =C95*(C90-Assumptions!$E$23*C92) -> 467712 | D104: =D95*(D90-Assumptions!$E$23*D92) -> 464889.6 | E104: =E95*(E90-Assumptions!$E$23*E92) -> 462078.89 | F104: =F95*(F90-Assumptions!$E$23*F92) -> 459279.81 | G104: =G95*(G90-Assumptions!$E$23*G92) -> 456492.27 | H104: =H95*(H90-Assumptions!$E$23*H92) -> 453716.22 | I104: =I95*(I90-Assumptions!$E$23*I92) -> 450951.59 | J104: =J95*(J90-Assumptions!$E$23*J92) -> 448198.29 | ... N104: =N95*(N90-Assumptions!$E$23*N92) -> 437297.16 | O104: =SUM(C104:N104) -> 5428803.3
